slash_remover_discord/__init__.py
slash_remover_discord-0.1.0.dist-info/METADATA
slash_remover_discord-0.1.0.dist-info/WHEEL
slash_remover_discord-0.1.0.dist-info/entry_points.txt
slash_remover_discord-0.1.0.dist-info/top_level.txt
slash_remover_discord-0.1.0.dist-info/RECORD
