Metadata-Version: 2.4
Name: slash-remover-discord
Version: 0.1.0
Summary: Clear all slash commands (global & guild) from your Discord bot
Author: Stark
Requires-Python: >=3.8
Requires-Dist: discord.py
